{
  "$schema": "https://zed.dev/schema/themes/v0.1.0.json",
  "name": "Wal System Theme",
  "author": "Generated by generate-wal-theme.sh",
  "themes": [
    {
      "appearance": "dark",
      "name": "Wal System Theme",
      "style": {
        "accents": [
          "#386684ff",
          "#384f98ff",
          "#37509aff",
          "#324685ff",
          "#4c63d7ff",
          "#4a60d7ff"
        ],
        "background.appearance": "opaque",
        "background":                        "#15202aff",
        "border":                            "#2e3943ff",
        "border.disabled":                   "#2940831a",
        "border.focused":                    "#386684ff",
        "border.selected":                   "#386684ff",
        "border.transparent":                "#00000000",
        "border.variant":                    "#2e3943b3",
        "conflict":                          "#37509aff",
        "conflict.background":               "#37509a1a",
        "conflict.border":                   "#37509a66",
        "created":                           "#384f98ff",
        "created.background":                "#384f9826",
        "created.border":                    "#384f9866",
        "deleted":                           "#324685ff",
        "deleted.background":                "#3246851a",
        "deleted.border":                    "#32468566",
        "drop_target.background":            "#3866841a",
        "editor.active_line.background":     "#1f2a34ff",
        "editor.active_line_number":         "#c1cafcff",
        "editor.active_wrap_guide":          "#2e3943b3",
        "editor.background":                 "#15202aff",
        "editor.document_highlight.read_background": "#3866844d",
        "editor.document_highlight.write_background": "#38668433",
        "editor.foreground":                 "#c1cafcff",
        "editor.gutter.background":          "#15202aff",
        "editor.highlighted_line.background":"#29408333",
        "editor.invisible":                  "#294083ff",
        "editor.line_number":                "#294083ff",
        "editor.subheader.background":       "#1f2a34ff",
        "editor.wrap_guide":                 "#2e3943b3",
        "element.active":                    "#29408333",
        "element.background":                "#29408333",
        "element.disabled":                  "#1b2630ff",
        "element.hover":                     "#29408333",
        "element.selected":                  "#29408333",
        "elevated_surface.background":       "#121d27ff",
        "error":                             "#324685ff",
        "error.background":                  "#1f2a34ff",
        "error.border":                      "#2e3943b3",
        "ghost_element.active":              "#29408333",
        "ghost_element.background":          "#00000000",
        "ghost_element.disabled":            "#1b2630ff",
        "ghost_element.hover":               "#29408333",
        "ghost_element.selected":            "#29408333",
        "hidden":                            "#294083ff",
        "hidden.background":                 "#1b2630ff",
        "hidden.border":                     "#2940831a",
        "hint":                              "#294083ff",
        "hint.background":                   "#1f2a34ff",
        "hint.border":                       "#2e3943b3",
        "icon":                              "#c1cafcff",
        "icon.background":                   "#15202aff",
        "icon.border":                       "#2e3943ff",
        "icon.accent":                       "#386684ff",
        "icon.muted":                        "#294083ff",
        "icon.disabled":                     "#294083ff",
        "ignored":                           "#294083ff",
        "ignored.background":                "#1b2630ff",
        "ignored.border":                    "#2940831a",
        "info":                              "#4a60d7ff",
        "info.background":                   "#1f2a34ff",
        "info.border":                       "#2e3943b3",
        "link_text.hover":                   "#386684ff",
        "modified":                          "#37509aff",
        "modified.background":               "#37509a26",
        "modified.border":                   "#37509a66",
        "pane.focused_border":               "#2e3943ff",
        "panel.background":                  "#121d27ff",
        "panel.focused_border":              "#2e3943ff",
        "predictive":                        "#294083ff",
        "predictive.background":             "#29408333",
        "predictive.border":                 "#2e3943b3",
        "renamed":                           "#384f98ff",
        "renamed.background":                "#384f9826",
        "renamed.border":                    "#384f9866",
        "scrollbar.thumb.border":            "#00000000",
        "scrollbar.thumb.hover_background":  "#29408366",
        "scrollbar.thumb.background":        "#2940834d",
        "scrollbar.track.background":        "#00000000",
        "scrollbar.track.border":            "#00000000",
        "search.match_background":           "#37509a4d",
        "status_bar.background":             "#121d27ff",
        "success":                           "#384f98ff",
        "success.background":                "#384f9826",
        "success.border":                    "#384f9866",
        "surface.background":                "#121d27ff",
        "tab.active_background":             "#15202aff",
        "tab.inactive_background":           "#121d27ff",
        "tab_bar.background":                "#121d27ff",
        "terminal.ansi.black":               "#15202aff",
        "terminal.ansi.bright_black":        "#294083ff",
        "terminal.ansi.dim_black":           "#15202aff",
        "terminal.ansi.blue":                "#386684ff",
        "terminal.ansi.bright_blue":         "#386684ff",
        "terminal.ansi.dim_blue":            "#386684ff",
        "terminal.ansi.cyan":                "#4a60d7ff",
        "terminal.ansi.bright_cyan":         "#4a60d7ff",
        "terminal.ansi.dim_cyan":            "#4a60d7ff",
        "terminal.ansi.green":               "#384f98ff",
        "terminal.ansi.bright_green":        "#384f98ff",
        "terminal.ansi.dim_green":           "#384f98ff",
        "terminal.ansi.magenta":             "#4c63d7ff",
        "terminal.ansi.bright_magenta":      "#4c63d7ff",
        "terminal.ansi.dim_magenta":         "#4c63d7ff",
        "terminal.ansi.red":                 "#324685ff",
        "terminal.ansi.bright_red":          "#324685ff",
        "terminal.ansi.dim_red":             "#324685ff",
        "terminal.ansi.white":               "#c1cafcff",
        "terminal.ansi.bright_white":        "#c1cafcff",
        "terminal.ansi.dim_white":           "#c1cafcff",
        "terminal.ansi.yellow":              "#37509aff",
        "terminal.ansi.bright_yellow":       "#37509aff",
        "terminal.ansi.dim_yellow":          "#37509aff",
        "terminal.background":               "#121d27ff",
        "terminal.bright_foreground":        "#c1cafcff",
        "terminal.dim_foreground":           "#294083ff",
        "terminal.foreground":               "#c1cafcff",
        "text":                              "#c1cafcff",
        "text.accent":                       "#386684ff",
        "text.disabled":                     "#294083ff",
        "text.muted":                        "#c1cafcff",
        "text.placeholder":                  "#294083ff",
        "title_bar.background":              "#121d27ff",
        "toolbar.background":                "#15202aff",
        "unreachable":                       "#294083ff",
        "unreachable.background":            "#1b2630ff",
        "unreachable.border":                "#2940831a",
        "vim.normal.foreground":             "#ffffffff",
        "vim.normal.background":             "#294083ff",
        "vim.helix_normal.foreground":       "#ffffffff",
        "vim.helix_normal.background":       "#294083ff",
        "vim.visual.foreground":             "#ffffffff",
        "vim.visual.background":             "#386684ff",
        "vim.helix_select.foreground":       "#ffffffff",
        "vim.helix_select.background":       "#386684ff",
        "vim.insert.foreground":             "#ffffffff",
        "vim.insert.background":             "#384f98ff",
        "vim.visual_line.foreground":        "#ffffffff",
        "vim.visual_line.background":        "#386684ff",
        "vim.visual_block.foreground":       "#ffffffff",
        "vim.visual_block.background":       "#4c63d7ff",
        "vim.replace.foreground":            "#ffffffff",
        "vim.replace.background":            "#324685ff",
        "warning":                           "#37509aff",
        "warning.background":                "#1f2a34ff",
        "warning.border":                    "#2e3943b3",
        "players": [
          { "cursor": "#386684ff",  "background": "#386684ff",  "selection": "#38668466" },
          { "cursor": "#384f98ff", "background": "#384f98ff", "selection": "#384f9866" },
          { "cursor": "#37509aff",    "background": "#37509aff",    "selection": "#37509a66" },
          { "cursor": "#324685ff", "background": "#324685ff", "selection": "#32468566" },
          { "cursor": "#4c63d7ff", "background": "#4c63d7ff", "selection": "#4c63d766" },
          { "cursor": "#4a60d7ff",    "background": "#4a60d7ff",    "selection": "#4a60d766" }
        ],
        "syntax": {
          "attribute":                  { "color": "#79c0ffff",    "font_style": null, "font_weight": null },
          "boolean":                    { "color": "#79c0ffff",    "font_style": null, "font_weight": null },
          "comment":                    { "color": "#9198a1ff",  "font_style": null, "font_weight": null },
          "comment.doc":                { "color": "#9198a1ff",  "font_style": null, "font_weight": null },
          "constant":                   { "color": "#79c0ffff",    "font_style": null, "font_weight": null },
          "constructor":                { "color": "#ff7b72ff",  "font_style": null, "font_weight": null },
          "embedded":                   { "color": "#ff7b72ff",  "font_style": null, "font_weight": null },
          "emphasis":                   { "color": null,                "font_style": "italic", "font_weight": null },
          "emphasis.strong":            { "color": null,                "font_style": null, "font_weight": 700 },
          "enum":                       { "color": "#ffa657ff",     "font_style": null, "font_weight": null },
          "function":                   { "color": "#d2a8ffff",     "font_style": null, "font_weight": null },
          "function.method":            { "color": "#d2a8ffff",     "font_style": null, "font_weight": null },
          "function.special.definition":{ "color": "#d2a8ffff",     "font_style": null, "font_weight": null },
          "hint":                       { "color": "#9198a1ff",  "font_style": null, "font_weight": 700 },
          "keyword":                    { "color": "#ff7b72ff",  "font_style": null, "font_weight": null },
          "keyword.operator":           { "color": "#ff7b72ff",  "font_style": null, "font_weight": null },
          "label":                      { "color": "#79c0ffff",    "font_style": null, "font_weight": null },
          "link_text":                  { "color": "#a5d6ffff",   "font_style": "italic", "font_weight": null },
          "link_uri":                   { "color": "#79c0ffff",    "font_style": null, "font_weight": null },
          "number":                     { "color": "#79c0ffff",    "font_style": null, "font_weight": null },
          "operator":                   { "color": "#ff7b72ff",  "font_style": null, "font_weight": null },
          "predictive":                 { "color": "#9198a1ff",  "font_style": "italic", "font_weight": null },
          "preproc":                    { "color": "#ff7b72ff",  "font_style": null, "font_weight": null },
          "primary":                    { "color": "#f0f6fcff",       "font_style": null, "font_weight": null },
          "property":                   { "color": "#f0f6fcff",     "font_style": null, "font_weight": null },
          "property.json_key":          { "color": "#7ee787ff",      "font_style": null, "font_weight": null },
          "punctuation":                { "color": "#ff7b72ff",  "font_style": null, "font_weight": null },
          "punctuation.bracket":        { "color": "#f0f6fcff",       "font_style": null, "font_weight": null },
          "punctuation.delimiter":      { "color": "#f0f6fcff",       "font_style": null, "font_weight": null },
          "punctuation.delimiter.jsx":  { "color": "#ff7b72ff",  "font_style": null, "font_weight": null },
          "punctuation.list_marker":    { "color": "#ffa657ff",     "font_style": null, "font_weight": null },
          "punctuation.special":        { "color": "#ff7b72ff",  "font_style": null, "font_weight": null },
          "string":                     { "color": "#a5d6ffff",   "font_style": null, "font_weight": null },
          "string.escape":              { "color": "#ff7b72ff",  "font_style": null, "font_weight": null },
          "string.regex":               { "color": "#a5d6ffff",   "font_style": null, "font_weight": null },
          "string.special":             { "color": "#79c0ffff",    "font_style": null, "font_weight": null },
          "string.special.symbol":      { "color": "#79c0ffff",    "font_style": null, "font_weight": null },
          "tag":                        { "color": "#7ee787ff",      "font_style": null, "font_weight": null },
          "text.literal":               { "color": "#79c0ffff",    "font_style": null, "font_weight": null },
          "title":                      { "color": "#79c0ffff",    "font_style": null, "font_weight": 700 },
          "type":                       { "color": "#ffa657ff",     "font_style": null, "font_weight": null },
          "type.builtin":               { "color": "#79c0ffff",    "font_style": null, "font_weight": null },
          "variable":                   { "color": "#f0f6fcff",       "font_style": null, "font_weight": null },
          "variable.builtin":           { "color": "#79c0ffff",    "font_style": null, "font_weight": null },
          "variable.parameter":         { "color": "#ffa657ff",     "font_style": null, "font_weight": null },
          "variable.special":           { "color": "#79c0ffff",    "font_style": null, "font_weight": null },
          "variant":                    { "color": "#ffa657ff",     "font_style": null, "font_weight": null }
        }
      }
    }
  ]
}
